[
    {
        "feature": "Мгновенный доступ специалистов к&nbsp;актуальным инструкциям"
    },
    {
        "feature": "Поиск как тексту, так и&nbsp;по&nbsp;смыслу"
    },
    {
        "feature": "Масштабируемость&nbsp;&mdash; возможность обработки миллионов документов"
    },
    {
        "feature": "Семантический движок на&nbsp;основе передовых архитектур глубоких нейронных сетей"
    },
    {
        "feature": "Возможность поиска по&nbsp;базе сканированных документов"
    },
    {
        "feature": "Контроль актуальности, копирования, сохранения и&nbsp;печати документов из&nbsp;системы"
    },
  
    {
        "feature": "Добавление в&nbsp;базу знаний документов &laquo;на&nbsp;лету&raquo;"
    },
    {
        "feature": "REST API для интеграции со&nbsp;сторонними системами"
    }
]